{"prefix":"tuy","outlets":[{"schemaVersion":1,"brand":"BPCL","outletId":"0000248848","stationId":"02274d3b266b4045","sourceUrl":"https://api.cep.bpcl.in/retail/v2/bpcl/retail/rolocator/details?roId=0000248848","capturedAt":"2026-07-21T17:21:06.251Z","name":"KAMAKHYA KASHYAP ENERGIES BHARAT PETROLEUM DEALERS","address":"TARKU TANAK GPU, TEMI, TARKU, NAMCHI, 737134, India","city":"Tarku","state":"Sikkim","pincode":"737134","lat":27.245916,"lng":88.441158,"geohash":"tuyfuxb","hours":null,"contact":"8918883566","mapsLink":null,"products":[{"name":"DIESEL","priceInr":97.55},{"name":"PETROL","priceInr":110.6}]},{"schemaVersion":1,"brand":"BPCL","outletId":"0000265436","stationId":"037c06678ba91465","sourceUrl":"https://api.cep.bpcl.in/retail/v2/bpcl/retail/rolocator/details?roId=0000265436","capturedAt":"2026-07-21T17:21:05.185Z","name":"BHARAT CHETRI FUELING STATION BHARAT PETROLEUM DEALERS","address":"PAIYONG GUMPA, PS LAVA, KALIMPONG, Kalimpong, 734314, India","city":"Kalimpong","state":"West Bengal","pincode":"734314","lat":27.103662,"lng":88.548714,"geohash":"tuyfnyp","hours":null,"contact":"8967390067","mapsLink":null,"products":[{"name":"DIESEL","priceInr":100.14},{"name":"PETROL","priceInr":113.81}]},{"schemaVersion":1,"brand":"BPCL","outletId":"0000120101","stationId":"0b67c4e1df535ed4","sourceUrl":"https://api.cep.bpcl.in/retail/v2/bpcl/retail/rolocator/details?roId=0000120101","capturedAt":"2026-07-21T17:21:06.251Z","name":"INDRAJMULL KURDAMULL BHARAT PETROLEUM DEALERS","address":"NH-10, RANGPO BAZAR, RANGPO, PAKYONG, Sikkim, 737132, India","city":"Rangpo","state":"Sikkim","pincode":"737132","lat":27.17409063,"lng":88.53136763,"geohash":"tuyfwdf","hours":null,"contact":"9434040865","mapsLink":null,"products":[{"name":"DIESEL","priceInr":97.55},{"name":"Hi-SPEED DIESEL","priceInr":0},{"name":"PETROL","priceInr":110.6},{"name":"SPEED","priceInr":0},{"name":"SPEED 97","priceInr":0}]},{"schemaVersion":1,"brand":"BPCL","outletId":"0000147646","stationId":"0dc749ae65340523","sourceUrl":"https://api.cep.bpcl.in/retail/v2/bpcl/retail/rolocator/details?roId=0000147646","capturedAt":"2026-07-21T17:21:05.185Z","name":"SHARDA AUTO CARE BHARAT PETROLEUM DEALERS","address":"P.O. PRADHANNAGAR, P.S PRADHANNAGAR, MALLAGURI, SILIGURI, DARJEELING, 734003, India","city":"Siliguri","state":"West Bengal","pincode":"734003","lat":26.73308226,"lng":88.4122355,"geohash":"tuyb5fe","hours":null,"contact":"9800258888","mapsLink":null,"products":[{"name":"DIESEL","priceInr":99.55},{"name":"PETROL","priceInr":113.18},{"name":"SPEED","priceInr":122.28}]},{"schemaVersion":1,"brand":"BPCL","outletId":"0000179607","stationId":"17162d00e5db5c80","sourceUrl":"https://api.cep.bpcl.in/retail/v2/bpcl/retail/rolocator/details?roId=0000179607","capturedAt":"2026-07-21T17:21:06.251Z","name":"GYAZING OIL DEPOT BHARAT PETROLEUM DEALERS","address":"GYALSHING, PO GYALSHING, Gayzing, GYALSHING, 737111, India","city":"Gayzing","state":"Sikkim","pincode":"737111","lat":27.28754553,"lng":88.25576999,"geohash":"tuyg0r9","hours":null,"contact":"9674988067","mapsLink":null,"products":[{"name":"DIESEL","priceInr":97.55},{"name":"Hi-SPEED DIESEL","priceInr":0},{"name":"PETROL","priceInr":110.6},{"name":"SPEED","priceInr":0},{"name":"SPEED 97","priceInr":0}]},{"schemaVersion":1,"brand":"BPCL","outletId":"0000254014","stationId":"1944183a57504fc1","sourceUrl":"https://api.cep.bpcl.in/retail/v2/bpcl/retail/rolocator/details?roId=0000254014","capturedAt":"2026-07-21T17:21:05.185Z","name":"TRINITY SERVICE STATION BHARAT PETROLEUM DEALERS","address":"DUDHIA, MIRIK ROAD, DUDHIA, DARJEELING, 734217, India","city":"Dudhia","state":"West Bengal","pincode":"734217","lat":26.821434,"lng":88.24585,"geohash":"tuyb84d","hours":null,"contact":"9800553159","mapsLink":null,"products":[{"name":"DIESEL","priceInr":99.58},{"name":"PETROL","priceInr":113.22}]},{"schemaVersion":1,"brand":"BPCL","outletId":"0000120071","stationId":"1a13326d8e391e69","sourceUrl":"https://api.cep.bpcl.in/retail/v2/bpcl/retail/rolocator/details?roId=0000120071","capturedAt":"2026-07-21T17:21:05.185Z","name":"HILL VIEW AUTO SERVICE BHARAT PETROLEUM DEALERS","address":"NH-55, SONADA, SONADA, DARJEELING, 734219, India","city":"Sonada","state":"West Bengal","pincode":"734219","lat":26.967683732322,"lng":88.273349312419,"geohash":"tuyc2tq","hours":null,"contact":"9832355980","mapsLink":null,"products":[{"name":"DIESEL","priceInr":101.23},{"name":"PETROL","priceInr":114.9}]},{"schemaVersion":1,"brand":"BPCL","outletId":"0000252446","stationId":"20195297a84e6241","sourceUrl":"https://api.cep.bpcl.in/retail/v2/bpcl/retail/rolocator/details?roId=0000252446","capturedAt":"2026-07-21T17:21:05.185Z","name":"SAWARIA SERVICE STATION BHARAT PETROLEUM DEALERS","address":"EASTERN BYPASS, ASHIGHAR, SILIGURI, JALPAIGURI, 734001, India","city":"Siliguri","state":"West Bengal","pincode":"734001","lat":26.7523108,"lng":88.4437302,"geohash":"tuybhw4","hours":null,"contact":"9434012523","mapsLink":null,"products":[{"name":"DIESEL","priceInr":99.59},{"name":"PETROL","priceInr":113.23},{"name":"SPEED","priceInr":122.32}]},{"schemaVersion":1,"brand":"BPCL","outletId":"0000191311","stationId":"23100ee475c32835","sourceUrl":"https://api.cep.bpcl.in/retail/v2/bpcl/retail/rolocator/details?roId=0000191311","capturedAt":"2026-07-21T17:21:05.509Z","name":"PADAMKAMAL FUELLING CENTRE BHARAT PETROLEUM DEALERS","address":"DENTAM, WEST SIKKIM, UTTARAY, GYALSHING, 737113, India","city":"Uttaray","state":"Sikkim","pincode":"737113","lat":27.263213344397,"lng":88.134224881007,"geohash":"tuyeje1","hours":null,"contact":"9735001687","mapsLink":null,"products":[{"name":"DIESEL","priceInr":97.55},{"name":"Hi-SPEED DIESEL","priceInr":0},{"name":"PETROL","priceInr":110.6},{"name":"SPEED","priceInr":0},{"name":"SPEED 97","priceInr":0}]},{"schemaVersion":1,"brand":"BPCL","outletId":"0000169678","stationId":"25675e05aa0acea6","sourceUrl":"https://api.cep.bpcl.in/retail/v2/bpcl/retail/rolocator/details?roId=0000169678","capturedAt":"2026-07-21T17:21:05.185Z","name":"FREE KICK VENTURES BHARAT PETROLEUM DEALERS","address":"NEAR SILIGURI REGULATED MARKET, MALLAGURI, SILIGURI, DARJEELING, 734001, India","city":"Siliguri","state":"West Bengal","pincode":"734001","lat":26.736532,"lng":88.4149,"geohash":"tuyb5gj","hours":null,"contact":"9681054799","mapsLink":null,"products":[{"name":"DIESEL","priceInr":99.59},{"name":"PETROL","priceInr":113.23},{"name":"SPEED","priceInr":122.32}]},{"schemaVersion":1,"brand":"BPCL","outletId":"0000212172","stationId":"2a24f8647f898a49","sourceUrl":"https://api.cep.bpcl.in/retail/v2/bpcl/retail/rolocator/details?roId=0000212172","capturedAt":"2026-07-21T17:21:05.185Z","name":"AARADHYA SERVICE STATION BHARAT PETROLEUM DEALERS","address":"MATIGARA, SILIGURI TOWN, MATIGARA, DARJEELING, 734010, India","city":"Matigara","state":"West Bengal","pincode":"734010","lat":26.723401,"lng":88.382543,"geohash":"tuyb50y","hours":null,"contact":"9832316674","mapsLink":null,"products":[]},{"schemaVersion":1,"brand":"BPCL","outletId":"0000120065","stationId":"3e0e0c476f925846","sourceUrl":"https://api.cep.bpcl.in/retail/v2/bpcl/retail/rolocator/details?roId=0000120065","capturedAt":"2026-07-21T17:21:05.185Z","name":"BILASRAI DALCHAND BHARAT PETROLEUM DEALERS","address":"SUKHIAPOKHRI, SUKHIAPOKHRI, SUKHIAPOKHRI, DARJEELING, 734221, India","city":"Sukhiapokhri","state":"West Bengal","pincode":"734221","lat":27.004881,"lng":88.171688,"geohash":"tuy9wkh","hours":null,"contact":"9932068249","mapsLink":null,"products":[{"name":"DIESEL","priceInr":100.73},{"name":"PETROL","priceInr":114.7},{"name":"SPEED","priceInr":123.68}]},{"schemaVersion":1,"brand":"BPCL","outletId":"0000194958","stationId":"3fe6997fb1b9d823","sourceUrl":"https://api.cep.bpcl.in/retail/v2/bpcl/retail/rolocator/details?roId=0000194958","capturedAt":"2026-07-21T17:21:05.185Z","name":"SAGAR SERVICE STATION (ADHOC) BHARAT PETROLEUM DEALERS","address":"NEAR KHAPRAIL MORE, MATIGARA, MATIGARA, DARJEELING, 734010, India","city":"Matigara","state":"West Bengal","pincode":"734010","lat":26.723401,"lng":88.382543,"geohash":"tuyb50y","hours":null,"contact":"9733006923","mapsLink":null,"products":[]},{"schemaVersion":1,"brand":"BPCL","outletId":"0000215453","stationId":"41b704705d82c601","sourceUrl":"https://api.cep.bpcl.in/retail/v2/bpcl/retail/rolocator/details?roId=0000215453","capturedAt":"2026-07-21T17:21:06.251Z","name":"KARMA FUEL CENTRE BHARAT PETROLEUM DEALERS","address":"JORETHANG, JORETHANG - MELLI ROAD, JORETHANG, SIKKIM SOUTH, 737121, India","city":"Jorethang","state":"Sikkim","pincode":"737121","lat":27.1308981,"lng":88.2856004,"geohash":"tuyf2gp","hours":null,"contact":"9002482244","mapsLink":null,"products":[{"name":"DIESEL","priceInr":97.55},{"name":"Hi-SPEED DIESEL","priceInr":0},{"name":"PETROL","priceInr":110.6},{"name":"SPEED","priceInr":0},{"name":"SPEED 97","priceInr":0}]},{"schemaVersion":1,"brand":"BPCL","outletId":"0000179296","stationId":"4760944e6e13237b","sourceUrl":"https://api.cep.bpcl.in/retail/v2/bpcl/retail/rolocator/details?roId=0000179296","capturedAt":"2026-07-21T17:21:06.251Z","name":"CACEY FUEL BHARAT PETROLEUM DEALERS","address":"ZERO POINT, RANGRANG, MANGAN, MANGAN, 737116, India","city":"Mangan","state":"Sikkim","pincode":"737116","lat":27.46506997,"lng":88.52492535,"geohash":"tuyunrv","hours":null,"contact":"9647192431","mapsLink":null,"products":[{"name":"DIESEL","priceInr":97.55},{"name":"Hi-SPEED DIESEL","priceInr":0},{"name":"PETROL","priceInr":110.6},{"name":"SPEED","priceInr":0},{"name":"SPEED 97","priceInr":0}]},{"schemaVersion":1,"brand":"BPCL","outletId":"0000253282","stationId":"47a9a8bf0d68144b","sourceUrl":"https://api.cep.bpcl.in/retail/v2/bpcl/retail/rolocator/details?roId=0000253282","capturedAt":"2026-07-21T17:21:06.251Z","name":"ANULOCHAN KHESANGHEY FUELS BHARAT PETROLEUM DEALERS","address":"NAMCHI-NAMTHANG ROAD, NAMCHI-NAMTHANG ROAD, NAMTHANG, NAMCHI, 737126, India","city":"Namthang","state":"Sikkim","pincode":"737126","lat":27.16758,"lng":88.47533,"geohash":"tuyft39","hours":null,"contact":"9907573949","mapsLink":null,"products":[{"name":"DIESEL","priceInr":97.55},{"name":"PETROL","priceInr":110.6}]},{"schemaVersion":1,"brand":"BPCL","outletId":"0000146553","stationId":"4ea64e8d65173c74","sourceUrl":"https://api.cep.bpcl.in/retail/v2/bpcl/retail/rolocator/details?roId=0000146553","capturedAt":"2026-07-21T17:21:06.251Z","name":"ROSHAN ENTERPRISE BHARAT PETROLEUM DEALERS","address":"P.O TUMIN, DIKCHU, DICKCHU, GANGTOK, 737101, India","city":"Dickchu","state":"Sikkim","pincode":"737101","lat":27.33642753,"lng":88.49094921,"geohash":"tuygt8m","hours":null,"contact":"7086110804","mapsLink":null,"products":[{"name":"DIESEL","priceInr":97.55},{"name":"Hi-SPEED DIESEL","priceInr":0},{"name":"PETROL","priceInr":110.6},{"name":"SPEED","priceInr":0},{"name":"SPEED 97","priceInr":0}]},{"schemaVersion":1,"brand":"BPCL","outletId":"0000120078","stationId":"548fb1897e86903a","sourceUrl":"https://api.cep.bpcl.in/retail/v2/bpcl/retail/rolocator/details?roId=0000120078","capturedAt":"2026-07-21T17:21:05.185Z","name":"RATIRAM BANSHILAL BHARAT PETROLEUM DEALERS","address":"TOPKHANA, RISHI ROAD, KALIMPONG TOWN, KALIMPONG, Kalimpong, 734301, India","city":"Kalimpong","state":"West Bengal","pincode":"734301","lat":27.07771663,"lng":88.48371149,"geohash":"tuyfj3r","hours":null,"contact":"9832039435","mapsLink":null,"products":[{"name":"DIESEL","priceInr":100.45},{"name":"PETROL","priceInr":114.3},{"name":"SPEED","priceInr":123.39}]},{"schemaVersion":1,"brand":"BPCL","outletId":"0000257516","stationId":"57ad253c6bbb864a","sourceUrl":"https://api.cep.bpcl.in/retail/v2/bpcl/retail/rolocator/details?roId=0000257516","capturedAt":"2026-07-21T17:21:06.251Z","name":"MAA TARA FUELS AND ENERGY BHARAT PETROLEUM DEALERS","address":"NAMCHI, NAMCHI, NAMCHI, NAMCHI, 737126, India","city":"Namchi","state":"Sikkim","pincode":"737126","lat":27.169748,"lng":88.377441,"geohash":"tuyfe44","hours":null,"contact":"8016961379","mapsLink":null,"products":[{"name":"DIESEL","priceInr":97.55},{"name":"PETROL","priceInr":110.6}]},{"schemaVersion":1,"brand":"BPCL","outletId":"0000243347","stationId":"5d390c29831b4840","sourceUrl":"https://api.cep.bpcl.in/retail/v2/bpcl/retail/rolocator/details?roId=0000243347","capturedAt":"2026-07-21T17:21:06.251Z","name":"TEESTA ENERGY ZONE BHARAT PETROLEUM DEALERS","address":"32 NO., NAMLI, GANGTOK, GANGTOK, 737135, India","city":"Gangtok","state":"Sikkim","pincode":"737135","lat":27.268651,"lng":88.578507,"geohash":"tuygpsh","hours":null,"contact":"6296016159","mapsLink":null,"products":[{"name":"DIESEL","priceInr":97.55},{"name":"PETROL","priceInr":110.6}]},{"schemaVersion":1,"brand":"BPCL","outletId":"0000120072","stationId":"5e6bf9b3667f1b91","sourceUrl":"https://api.cep.bpcl.in/retail/v2/bpcl/retail/rolocator/details?roId=0000120072","capturedAt":"2026-07-21T17:21:05.185Z","name":"MATIGARA SERVICE STN. BHARAT PETROLEUM DEALERS","address":"MATIGARA, MATIGARA, MATIGARA, DARJEELING WEST BENG, 734010, India","city":"Matigara","state":"West Bengal","pincode":"734010","lat":26.723401,"lng":88.382543,"geohash":"tuyb50y","hours":null,"contact":"9832016676","mapsLink":null,"products":[]},{"schemaVersion":1,"brand":"BPCL","outletId":"0000157696","stationId":"654a107042cc7fec","sourceUrl":"https://api.cep.bpcl.in/retail/v2/bpcl/retail/rolocator/details?roId=0000157696","capturedAt":"2026-07-21T17:21:06.251Z","name":"PANKAJ FUEL CENTER BHARAT PETROLEUM DEALERS","address":"P.O. MAJITAR, P.S. RANGPO, RANGPO, PAKYONG, 737132, India","city":"Rangpo","state":"Sikkim","pincode":"737132","lat":27.187691,"lng":88.49917,"geohash":"tuyftv7","hours":null,"contact":"9933662424","mapsLink":null,"products":[{"name":"DIESEL","priceInr":97.55},{"name":"Hi-SPEED DIESEL","priceInr":0},{"name":"PETROL","priceInr":110.6},{"name":"SPEED","priceInr":119.6},{"name":"SPEED 97","priceInr":0}]},{"schemaVersion":1,"brand":"BPCL","outletId":"0000120079","stationId":"68c41492d5bf3815","sourceUrl":"https://api.cep.bpcl.in/retail/v2/bpcl/retail/rolocator/details?roId=0000120079","capturedAt":"2026-07-21T17:21:05.185Z","name":"SAGAR SERVICE STN. BHARAT PETROLEUM DEALERS","address":"2ND MILE, SILIGURI, EKTIASAL, JALPAIGURI, 734001, India","city":"Ektiasal","state":"West Bengal","pincode":"734001","lat":26.742085,"lng":88.4361,"geohash":"tuybhkj","hours":null,"contact":"9733006923","mapsLink":null,"products":[{"name":"DIESEL","priceInr":99.59},{"name":"PETROL","priceInr":113.23},{"name":"SPEED","priceInr":122.32}]},{"schemaVersion":1,"brand":"BPCL","outletId":"0000188196","stationId":"69aec12d0d92f16e","sourceUrl":"https://api.cep.bpcl.in/retail/v2/bpcl/retail/rolocator/details?roId=0000188196","capturedAt":"2026-07-21T17:21:06.251Z","name":"PELLING FUEL CENTRE BHARAT PETROLEUM DEALERS","address":"NAKU, LOWER PELLING, PELLING, GYALSHING, 737113, India","city":"Pelling","state":"Sikkim","pincode":"737113","lat":27.30168237,"lng":88.23753011,"geohash":"tuyerfh","hours":null,"contact":"7557844044","mapsLink":null,"products":[{"name":"DIESEL","priceInr":97.55},{"name":"Hi-SPEED DIESEL","priceInr":0},{"name":"PETROL","priceInr":110.6},{"name":"SPEED","priceInr":0},{"name":"SPEED 97","priceInr":0}]},{"schemaVersion":1,"brand":"BPCL","outletId":"0000249150","stationId":"6f6e66ef7a3958b9","sourceUrl":"https://api.cep.bpcl.in/retail/v2/bpcl/retail/rolocator/details?roId=0000249150","capturedAt":"2026-07-21T17:21:05.185Z","name":"RELLI RIVERSIDE FUEL STATION BHARAT PETROLEUM DEALERS","address":"PUDUNG, KALIMPONG, KALIMPONG, Kalimpong, 734301, India","city":"Kalimpong","state":"West Bengal","pincode":"734301","lat":27.0586,"lng":88.5273,"geohash":"tuycymz","hours":null,"contact":"7001032301","mapsLink":null,"products":[{"name":"DIESEL","priceInr":100.19},{"name":"PETROL","priceInr":113.87}]},{"schemaVersion":1,"brand":"BPCL","outletId":"0000250919","stationId":"70088bd736ca9017","sourceUrl":"https://api.cep.bpcl.in/retail/v2/bpcl/retail/rolocator/details?roId=0000250919","capturedAt":"2026-07-21T17:21:05.185Z","name":"FOOTHILLS SERVICE STATION ADHO BHARAT PETROLEUM DEALERS","address":"KHAPRAIL, SH-12, MATIGARA, DARJEELING, 734010, India","city":"Matigara","state":"West Bengal","pincode":"734010","lat":26.723401,"lng":88.382543,"geohash":"tuyb50y","hours":null,"contact":"8927729553","mapsLink":null,"products":[]},{"schemaVersion":1,"brand":"BPCL","outletId":"0000179608","stationId":"75bf82a56c0c31e2","sourceUrl":"https://api.cep.bpcl.in/retail/v2/bpcl/retail/rolocator/details?roId=0000179608","capturedAt":"2026-07-21T17:21:06.251Z","name":"TASHIDING PETROL PUMP BHARAT PETROLEUM DEALERS","address":"TASHIDING BAZAR, O P SINEK, Senik, GYALSHING, 737111, India","city":"Senik","state":"Sikkim","pincode":"737111","lat":27.324753552353,"lng":88.286991158511,"geohash":"tuyg3n2","hours":null,"contact":"7478545107","mapsLink":null,"products":[{"name":"DIESEL","priceInr":97.55},{"name":"Hi-SPEED DIESEL","priceInr":0},{"name":"PETROL","priceInr":110.6},{"name":"SPEED","priceInr":0},{"name":"SPEED 97","priceInr":0}]},{"schemaVersion":1,"brand":"BPCL","outletId":"0000120061","stationId":"78eb184565dfe163","sourceUrl":"https://api.cep.bpcl.in/retail/v2/bpcl/retail/rolocator/details?roId=0000120061","capturedAt":"2026-07-21T17:21:05.185Z","name":"AUTO POINT BHARAT PETROLEUM DEALERS","address":"DARJEELING TOWN, DARJEELING, DARJEELING, DARJEELING, 734101, India","city":"Darjeeling","state":"West Bengal","pincode":"734101","lat":27.04120064,"lng":88.26439667,"geohash":"tuycbd8","hours":null,"contact":"9474962011","mapsLink":null,"products":[{"name":"DIESEL","priceInr":101.14},{"name":"PETROL","priceInr":114.75}]},{"schemaVersion":1,"brand":"BPCL","outletId":"0000215455","stationId":"80ba919b0fa884ce","sourceUrl":"https://api.cep.bpcl.in/retail/v2/bpcl/retail/rolocator/details?roId=0000215455","capturedAt":"2026-07-21T17:21:05.185Z","name":"FOOTHILLS SERVICE STATION BHARAT PETROLEUM DEALERS","address":"KHAPRAIL, SH-12, SILIGURI, DARJEELING, 734001, India","city":"Siliguri","state":"West Bengal","pincode":"734001","lat":26.75136,"lng":88.34769,"geohash":"tuyb4mu","hours":null,"contact":"8509915257","mapsLink":null,"products":[{"name":"DIESEL","priceInr":99.59},{"name":"PETROL","priceInr":113.23},{"name":"SPEED","priceInr":122.32}]},{"schemaVersion":1,"brand":"BPCL","outletId":"0000120084","stationId":"97ec4c0f15402abe","sourceUrl":"https://api.cep.bpcl.in/retail/v2/bpcl/retail/rolocator/details?roId=0000120084","capturedAt":"2026-07-21T17:21:05.185Z","name":"TOWN STORES BHARAT PETROLEUM DEALERS","address":"SILIGURI TOWN, SILIGURI, SILIGURI, DARJEELING, 734001, India","city":"Siliguri","state":"West Bengal","pincode":"734001","lat":26.730544,"lng":88.41227,"geohash":"tuyb5f5","hours":null,"contact":"9647822263","mapsLink":null,"products":[{"name":"DIESEL","priceInr":99.59},{"name":"PETROL","priceInr":113.23},{"name":"SPEED","priceInr":122.32}]},{"schemaVersion":1,"brand":"BPCL","outletId":"0000156162","stationId":"9af86d5993c6f29e","sourceUrl":"https://api.cep.bpcl.in/retail/v2/bpcl/retail/rolocator/details?roId=0000156162","capturedAt":"2026-07-21T17:21:06.251Z","name":"KAMAKHAYA FUEL BHARAT PETROLEUM DEALERS","address":"P.O.SORENG, SORENG - KALUK ROAD, SORENG, SORENG, 737121, India","city":"Soreng","state":"Sikkim","pincode":"737121","lat":27.17568253775,"lng":88.197515382338,"geohash":"tuydwgp","hours":null,"contact":"9733138406","mapsLink":null,"products":[{"name":"DIESEL","priceInr":97.55},{"name":"Hi-SPEED DIESEL","priceInr":0},{"name":"PETROL","priceInr":110.6},{"name":"SPEED","priceInr":0},{"name":"SPEED 97","priceInr":0}]},{"schemaVersion":1,"brand":"BPCL","outletId":"0000146551","stationId":"9e9be6ba872ef5a8","sourceUrl":"https://api.cep.bpcl.in/retail/v2/bpcl/retail/rolocator/details?roId=0000146551","capturedAt":"2026-07-21T17:21:05.185Z","name":"GOENKA & CO. BHARAT PETROLEUM DEALERS","address":"PS KURSEONG, NH-55, TUNG, DARJEELING, 734224, India","city":"Tung","state":"West Bengal","pincode":"734224","lat":26.92207,"lng":88.309822,"geohash":"tuyc1t1","hours":null,"contact":"9830225659","mapsLink":null,"products":[]},{"schemaVersion":1,"brand":"BPCL","outletId":"0000120076","stationId":"a31095bf22ec076b","sourceUrl":"https://api.cep.bpcl.in/retail/v2/bpcl/retail/rolocator/details?roId=0000120076","capturedAt":"2026-07-21T17:21:05.185Z","name":"R.N.AGARWALA & SON BHARAT PETROLEUM DEALERS","address":"DALI, WEST POINT, DARJEELING, DARJEELING, 734101, India","city":"Darjeeling","state":"West Bengal","pincode":"734101","lat":27.024092350389,"lng":88.253768828824,"geohash":"tuyc8r8","hours":null,"contact":"9434752082","mapsLink":null,"products":[{"name":"DIESEL","priceInr":101.25},{"name":"PETROL","priceInr":114.8},{"name":"SPEED","priceInr":123.83}]},{"schemaVersion":1,"brand":"BPCL","outletId":"0000179673","stationId":"a77982c6ea26eff0","sourceUrl":"https://api.cep.bpcl.in/retail/v2/bpcl/retail/rolocator/details?roId=0000179673","capturedAt":"2026-07-21T17:21:06.251Z","name":"MAINAM FUEL BHARAT PETROLEUM DEALERS","address":"GAGYONG, YANGYANG, Rabangla, NAMCHI, 737134, India","city":"Rabangla","state":"Sikkim","pincode":"737134","lat":27.29404119,"lng":88.4194111,"geohash":"tuygk09","hours":null,"contact":"9002350399","mapsLink":null,"products":[{"name":"DIESEL","priceInr":97.55},{"name":"Hi-SPEED DIESEL","priceInr":0},{"name":"PETROL","priceInr":110.6},{"name":"SPEED","priceInr":0},{"name":"SPEED 97","priceInr":0}]},{"schemaVersion":1,"brand":"BPCL","outletId":"0000174650","stationId":"af553c953314382d","sourceUrl":"https://api.cep.bpcl.in/retail/v2/bpcl/retail/rolocator/details?roId=0000174650","capturedAt":"2026-07-21T17:21:05.185Z","name":"SONA PETROL PUMP BHARAT PETROLEUM DEALERS","address":"SALUGARA, 3RD MILE, SEVOKE ROAD, DIST JALPAIGURI, SILIGURI, JALPAIGURI, 734008, India","city":"Siliguri","state":"West Bengal","pincode":"734008","lat":26.756505,"lng":88.440965,"geohash":"tuybhwb","hours":null,"contact":"9474390332","mapsLink":null,"products":[{"name":"DIESEL","priceInr":99.59},{"name":"PETROL","priceInr":113.23},{"name":"SPEED","priceInr":122.32}]},{"schemaVersion":1,"brand":"BPCL","outletId":"0000120069","stationId":"b5aa730c84e20e6a","sourceUrl":"https://api.cep.bpcl.in/retail/v2/bpcl/retail/rolocator/details?roId=0000120069","capturedAt":"2026-07-21T17:21:05.185Z","name":"GOENKA & CO. SALES P. LTD. BHARAT PETROLEUM DEALERS","address":"AT KURSEONG, HILL CART ROAD, KURSEONG, DARJEELING, 734203, India","city":"Kurseong","state":"West Bengal","pincode":"734203","lat":26.87821864,"lng":88.27746799,"geohash":"tuybbv1","hours":null,"contact":"9933064152","mapsLink":null,"products":[{"name":"DIESEL","priceInr":101.1},{"name":"PETROL","priceInr":114.91}]},{"schemaVersion":1,"brand":"BPCL","outletId":"0000253494","stationId":"b68c38e5f66ecaa6","sourceUrl":"https://api.cep.bpcl.in/retail/v2/bpcl/retail/rolocator/details?roId=0000253494","capturedAt":"2026-07-21T17:21:06.251Z","name":"JKB FUELS BHARAT PETROLEUM DEALERS","address":"LOWER MAMRING, NAMCHI - NAMTHANG ROAD, GANGTOK, NAMCHI, 737132, India","city":"Gangtok","state":"Sikkim","pincode":"737132","lat":27.171957,"lng":88.516733,"geohash":"tuyfw4x","hours":null,"contact":"6295072930","mapsLink":null,"products":[{"name":"DIESEL","priceInr":97.55},{"name":"PETROL","priceInr":110.6}]},{"schemaVersion":1,"brand":"BPCL","outletId":"0000120100","stationId":"c13438cb8d5ae90b","sourceUrl":"https://api.cep.bpcl.in/retail/v2/bpcl/retail/rolocator/details?roId=0000120100","capturedAt":"2026-07-21T17:21:06.251Z","name":"CHANDRA SALES AGENCY BHARAT PETROLEUM DEALERS","address":"NAYA BAZAR, JORETHANG, JORETHANG, SORENG, Sikkim, 737121, India","city":"Jorethang","state":"Sikkim","pincode":"737121","lat":27.1317196,"lng":88.2796278,"geohash":"tuyf2g5","hours":null,"contact":"9434179107","mapsLink":null,"products":[{"name":"DIESEL","priceInr":97.55},{"name":"Hi-SPEED DIESEL","priceInr":0},{"name":"PETROL","priceInr":110.6},{"name":"SPEED","priceInr":0},{"name":"SPEED 97","priceInr":0}]},{"schemaVersion":1,"brand":"BPCL","outletId":"0000180610","stationId":"ca3c8653a538000b","sourceUrl":"https://api.cep.bpcl.in/retail/v2/bpcl/retail/rolocator/details?roId=0000180610","capturedAt":"2026-07-21T17:21:06.251Z","name":"MAINAM OIL DISTRIBUTOR BHARAT PETROLEUM DEALERS","address":"RAVONGLA, RAVONGLA, Ravongla, NAMCHI, 737139, India","city":"Ravongla","state":"Sikkim","pincode":"737139","lat":27.310595003345,"lng":88.362120609209,"geohash":"tuyg6ex","hours":null,"contact":"9434144012","mapsLink":null,"products":[{"name":"DIESEL","priceInr":97.55},{"name":"Hi-SPEED DIESEL","priceInr":0},{"name":"PETROL","priceInr":110.6},{"name":"SPEED","priceInr":0},{"name":"SPEED 97","priceInr":0}]},{"schemaVersion":1,"brand":"BPCL","outletId":"0000155254","stationId":"ca52ffe012f6e3a1","sourceUrl":"https://api.cep.bpcl.in/retail/v2/bpcl/retail/rolocator/details?roId=0000155254","capturedAt":"2026-07-21T17:21:06.251Z","name":"KANCHENJUNGA FILLING STATION BHARAT PETROLEUM DEALERS","address":"KEWZING BAZAR, SUB-DIVISION RAVONGLA, RAVANGLA, NAMCHI, 737134, India","city":"Ravangla","state":"Sikkim","pincode":"737134","lat":27.2479471,"lng":88.5081765,"geohash":"tuygn03","hours":null,"contact":"9475300327","mapsLink":null,"products":[{"name":"DIESEL","priceInr":0},{"name":"Hi-SPEED DIESEL","priceInr":0},{"name":"PETROL","priceInr":0},{"name":"SPEED","priceInr":0},{"name":"SPEED 97","priceInr":0}]},{"schemaVersion":1,"brand":"BPCL","outletId":"0000171327","stationId":"ca609d1a6fbcd96b","sourceUrl":"https://api.cep.bpcl.in/retail/v2/bpcl/retail/rolocator/details?roId=0000171327","capturedAt":"2026-07-21T17:21:06.251Z","name":"ETERNAL OIL DISTRIBUTOR BHARAT PETROLEUM DEALERS","address":"NAKUDARA (BETWEEN DARAMDIN & SOMBAR, PO-SOMBARIA, SOMBARIA, SORENG, 737121, India","city":"Sombaria","state":"Sikkim","pincode":"737121","lat":27.142512045462,"lng":88.147945057816,"geohash":"tuydmv5","hours":null,"contact":"9474692237","mapsLink":null,"products":[{"name":"DIESEL","priceInr":97.55},{"name":"Hi-SPEED DIESEL","priceInr":0},{"name":"PETROL","priceInr":110.6},{"name":"SPEED","priceInr":0},{"name":"SPEED 97","priceInr":0}]},{"schemaVersion":1,"brand":"BPCL","outletId":"0000244397","stationId":"ce7145397ee329f1","sourceUrl":"https://api.cep.bpcl.in/retail/v2/bpcl/retail/rolocator/details?roId=0000244397","capturedAt":"2026-07-21T17:21:05.185Z","name":"HILL VIEW FUELS ADHOC BHARAT PETROLEUM DEALERS","address":"MATHAPARI, NEAR KHAPRAIL MORE, MATIGARA, DARJEELING, 734010, India","city":"Matigara","state":"West Bengal","pincode":"734010","lat":26.723401,"lng":88.382543,"geohash":"tuyb50y","hours":null,"contact":"9832427690","mapsLink":null,"products":[{"name":"DIESEL","priceInr":99.59},{"name":"PETROL","priceInr":113.23},{"name":"SPEED","priceInr":122.32}]},{"schemaVersion":1,"brand":"BPCL","outletId":"0000149438","stationId":"dbc037c2a25b2b38","sourceUrl":"https://api.cep.bpcl.in/retail/v2/bpcl/retail/rolocator/details?roId=0000149438","capturedAt":"2026-07-21T17:21:06.251Z","name":"HILL SHIP FUELS BHARAT PETROLEUM DEALERS","address":"PIPELEY, LLEGSHIP ROAD, JORETHANG, SORENG, 737121, India","city":"Jorethang","state":"Sikkim","pincode":"737121","lat":27.14688203,"lng":88.2797412,"geohash":"tuyf2vg","hours":null,"contact":"9733165320","mapsLink":null,"products":[{"name":"DIESEL","priceInr":97.55},{"name":"Hi-SPEED DIESEL","priceInr":0},{"name":"PETROL","priceInr":110.6},{"name":"SPEED","priceInr":0},{"name":"SPEED 97","priceInr":0}]},{"schemaVersion":1,"brand":"BPCL","outletId":"0000218348","stationId":"dc5bfdf069bff806","sourceUrl":"https://api.cep.bpcl.in/retail/v2/bpcl/retail/rolocator/details?roId=0000218348","capturedAt":"2026-07-21T17:21:05.185Z","name":"BIJANBARI FUEL CENTRE BHARAT PETROLEUM DEALERS","address":"BIJANBARI, NEAR BIJANBARI POST OFFICE, DARJEELING, DARJEELING, 734201, India","city":"Darjeeling","state":"West Bengal","pincode":"734201","lat":27.073819043657,"lng":88.1998011183,"geohash":"tuydp09","hours":null,"contact":"8016245589","mapsLink":null,"products":[{"name":"DIESEL","priceInr":100.8},{"name":"PETROL","priceInr":114.62}]},{"schemaVersion":1,"brand":"BPCL","outletId":"0000142165","stationId":"e9775cbbb653483b","sourceUrl":"https://api.cep.bpcl.in/retail/v2/bpcl/retail/rolocator/details?roId=0000142165","capturedAt":"2026-07-21T17:21:05.185Z","name":"HILL VIEW FUELS BHARAT PETROLEUM DEALERS","address":"PS- MATIGARA, P.O-SUKNA, NH-55, SUKNA, DARJEELING, 734009, India","city":"Sukna","state":"West Bengal","pincode":"734009","lat":26.770177,"lng":88.378369,"geohash":"tuyb717","hours":null,"contact":"7477430444","mapsLink":null,"products":[{"name":"DIESEL","priceInr":99.55},{"name":"PETROL","priceInr":113.18},{"name":"SPEED","priceInr":122.28}]},{"schemaVersion":1,"brand":"BPCL","outletId":"0000149033","stationId":"f2e9076d9d9d968e","sourceUrl":"https://api.cep.bpcl.in/retail/v2/bpcl/retail/rolocator/details?roId=0000149033","capturedAt":"2026-07-21T17:21:06.251Z","name":"BHAGIRATHI & SONS FUELLING STA BHARAT PETROLEUM DEALERS","address":"6TH MILE, P.O. SANGUR, TADONG, NH31A, GANGTOK, SIKKIM EAST, 737102, India","city":"Gangtok","state":"Sikkim","pincode":"737102","lat":27.312168,"lng":88.590382,"geohash":"tuygruj","hours":null,"contact":"8617674728","mapsLink":null,"products":[{"name":"DIESEL","priceInr":97.55},{"name":"Hi-SPEED DIESEL","priceInr":0},{"name":"PETROL","priceInr":110.6},{"name":"SPEED","priceInr":119.6},{"name":"SPEED 97","priceInr":0}]}]}